bfs/__init__.py
bfs/config/__init__.py
bfs/config/settings.py
bfs/config/tests/__init__.py
bfs/config/tests/test_settings.py
bfs/database/__init__.py
bfs/database/database.py
bfs/database/tests/__init__.py
bfs/database/tests/test_database.py
base_flask_structure-1.0.0.dist-info/LICENSE
base_flask_structure-1.0.0.dist-info/METADATA
base_flask_structure-1.0.0.dist-info/WHEEL
base_flask_structure-1.0.0.dist-info/top_level.txt
base_flask_structure-1.0.0.dist-info/RECORD
