Metadata-Version: 2.1
Name: base-flask-structure
Version: 1.0.0
Summary: Easily include basic functions on your apps.
Author-email: Jodagito <jodagito@gmail.com>
License: MIT License
Project-URL: Homepage, https://github.com/Jodagito/base_flask_structure
Keywords: flask,sqlalchemy,dotenv,base
Classifier: License :: OSI Approved :: MIT License
Classifier: Programming Language :: Python
Classifier: Programming Language :: Python :: 3
Requires-Python: >=3.11
License-File: LICENSE
Requires-Dist: python-dotenv
Requires-Dist: flask-sqlalchemy
Requires-Dist: psycopg2
Provides-Extra: dev
Requires-Dist: pytest ; extra == 'dev'
